ner_analyzer/__init__.py
ner_analyzer/analyzer.py
ner_analyzer/cli.py
ner_analyzer/utils.py
ner_analyzer_cli_v2-0.3.dist-info/METADATA
ner_analyzer_cli_v2-0.3.dist-info/WHEEL
ner_analyzer_cli_v2-0.3.dist-info/entry_points.txt
ner_analyzer_cli_v2-0.3.dist-info/top_level.txt
ner_analyzer_cli_v2-0.3.dist-info/RECORD
